[{"line":3,"elements":[{"start_timestamp":"2022-10-25T16:51:13.885Z","before":[{"result":{"error_message":"org.openqa.selenium.SessionNotCreatedException: Could not start a new session. Response code 500. Message: session not created: This version of ChromeDriver only supports Chrome version 103\nCurrent browser version is 106.0.5249.119 with binary path C:\\Program Files\\Google\\Chrome\\Application\\chrome.exe\nBuild info: version: '4.2.1', revision: 'ac4d0fdd4a'\nSystem info: host: 'UDI-3P7F8K3', ip: '192.168.1.106', os.name: 'Windows 10', os.arch: 'amd64', os.version: '10.0', java.version: '19.0.1'\nDriver info: org.openqa.selenium.chrome.ChromeDriver\nCommand: [null, newSession {capabilities=[Capabilities {browserName: chrome, goog:chromeOptions: {args: [], extensions: []}}], desiredCapabilities=Capabilities {browserName: chrome, goog:chromeOptions: {args: [], extensions: []}}}]\r\n\tat org.openqa.selenium.remote.ProtocolHandshake.createSession(ProtocolHandshake.java:144)\r\n\tat org.openqa.selenium.remote.ProtocolHandshake.createSession(ProtocolHandshake.java:102)\r\n\tat org.openqa.selenium.remote.ProtocolHandshake.createSession(ProtocolHandshake.java:67)\r\n\tat org.openqa.selenium.remote.HttpCommandExecutor.execute(HttpCommandExecutor.java:156)\r\n\tat org.openqa.selenium.remote.service.DriverCommandExecutor.invokeExecute(DriverCommandExecutor.java:167)\r\n\tat org.openqa.selenium.remote.service.DriverCommandExecutor.execute(DriverCommandExecutor.java:142)\r\n\tat org.openqa.selenium.remote.RemoteWebDriver.execute(RemoteWebDriver.java:551)\r\n\tat org.openqa.selenium.remote.RemoteWebDriver.startSession(RemoteWebDriver.java:246)\r\n\tat org.openqa.selenium.remote.RemoteWebDriver.<init>(RemoteWebDriver.java:162)\r\n\tat org.openqa.selenium.chromium.ChromiumDriver.<init>(ChromiumDriver.java:106)\r\n\tat org.openqa.selenium.chrome.ChromeDriver.<init>(ChromeDriver.java:106)\r\n\tat org.openqa.selenium.chrome.ChromeDriver.<init>(ChromeDriver.java:93)\r\n\tat org.openqa.selenium.chrome.ChromeDriver.<init>(ChromeDriver.java:48)\r\n\tat com.nttdata.stepsdefinitions.LoginStepsDef.setUp(LoginStepsDef.java:32)\r\n","duration":2324223700,"status":"failed"},"match":{"location":"com.nttdata.stepsdefinitions.LoginStepsDef.setUp()"}},{"result":{"status":"passed"},"match":{"location":"com.nttdata.stepsdefinitions.LoginStepsDef.setScenario(io.cucumber.java.Scenario)"}}],"line":9,"name":"Iniciar sesión","description":"","id":"login;iniciar-sesión","after":[{"result":{"error_message":"java.lang.NullPointerException: Cannot invoke \"org.openqa.selenium.WebDriver.quit()\" because \"this.driver\" is null\r\n\tat com.nttdata.stepsdefinitions.LoginStepsDef.quitDriver(LoginStepsDef.java:44)\r\n","duration":986100,"status":"failed"},"match":{"location":"com.nttdata.stepsdefinitions.LoginStepsDef.quitDriver()"}}],"type":"scenario","keyword":"Escenario","steps":[{"result":{"status":"skipped"},"line":10,"name":"que me encuentro en la página de login de Saucedemo","match":{"location":"com.nttdata.stepsdefinitions.LoginStepsDef.que_me_encuentro_en_la_página_de_login_de_sacedemo()"},"keyword":"Dado "},{"result":{"duration":545000,"status":"skipped"},"line":11,"name":"inicio sesión con las credenciales usuario: \"standard_user\" y contraseña: \"secret_sauce\"","match":{"arguments":[{"val":"\"standard_user\"","offset":44},{"val":"\"secret_sauce\"","offset":74}],"location":"com.nttdata.stepsdefinitions.LoginStepsDef.inicio_sesión_con_las_credenciales_usuario_y_contraseña(java.lang.String,java.lang.String)"},"keyword":"Cuando "},{"result":{"duration":501300,"status":"skipped"},"line":12,"name":"valido que debería aparecer el título de \"PRODUCTS\"","match":{"arguments":[{"val":"\"PRODUCTS\"","offset":41}],"location":"com.nttdata.stepsdefinitions.LoginStepsDef.valido_que_debería_aparecer_el_título_de(java.lang.String)"},"keyword":"Entonces "},{"result":{"status":"skipped"},"line":13,"name":"también valido que al menos exista un item","match":{"location":"com.nttdata.stepsdefinitions.LoginStepsDef.también_valido_que_al_menos_exista_un_item()"},"keyword":"Y "}],"tags":[{"name":"@testfeature"},{"name":"@test"}]}],"name":"Login","description":"  Yo, como usuario\n  Quiero, tener una opción para iniciar sesión\n  Para ver todos los items","id":"login","keyword":"Característica","uri":"file:src/test/resources/features/login.feature","tags":[{"name":"@testfeature","type":"Tag","location":{"line":2,"column":1}}]}]